[{"inputs": [], "constant": true, "name": "creator", "payable": false, "outputs": [{"type": "address", "name": ""}], "type": "function"}, {"inputs": [], "constant": true, "name": "marketMaker", "payable": false, "outputs": [{"type": "address", "name": ""}], "type": "function"}, {"inputs": [{"type": "uint8", "name": "outcomeTokenIndex"}, {"type": "uint256", "name": "outcomeTokenCount"}, {"type": "uint256", "name": "minProfit"}], "constant": false, "name": "shortSell", "payable": false, "outputs": [{"type": "uint256", "name": "cost"}], "type": "function"}, {"inputs": [], "constant": false, "name": "close", "payable": false, "outputs": [], "type": "function"}, {"inputs": [{"type": "uint8", "name": "outcomeTokenIndex"}, {"type": "uint256", "name": "outcomeTokenCount"}, {"type": "uint256", "name": "minProfit"}], "constant": false, "name": "sell", "payable": false, "outputs": [{"type": "uint256", "name": "profit"}], "type": "function"}, {"inputs": [], "constant": false, "name": "withdrawFees", "payable": false, "outputs": [{"type": "uint256", "name": "fees"}], "type": "function"}, {"inputs": [], "constant": true, "name": "createdAtBlock", "payable": false, "outputs": [{"type": "uint256", "name": ""}], "type": "function"}, {"inputs": [{"type": "uint256", "name": ""}], "constant": true, "name": "netOutcomeTokensSold", "payable": false, "outputs": [{"type": "int256", "name": ""}], "type": "function"}, {"inputs": [{"type": "uint256", "name": "outcomeTokenCost"}], "constant": true, "name": "calcMarketFee", "payable": false, "outputs": [{"type": "uint256", "name": ""}], "type": "function"}, {"inputs": [], "constant": true, "name": "stage", "payable": false, "outputs": [{"type": "uint8", "name": ""}], "type": "function"}, {"inputs": [{"type": "uint256", "name": "_funding"}], "constant": false, "name": "fund", "payable": false, "outputs": [], "type": "function"}, {"inputs": [], "constant": true, "name": "funding", "payable": false, "outputs": [{"type": "uint256", "name": ""}], "type": "function"}, {"inputs": [], "constant": true, "name": "fee", "payable": false, "outputs": [{"type": "uint24", "name": ""}], "type": "function"}, {"inputs": [], "constant": true, "name": "eventContract", "payable": false, "outputs": [{"type": "address", "name": ""}], "type": "function"}, {"inputs": [{"type": "uint8", "name": "outcomeTokenIndex"}, {"type": "uint256", "name": "outcomeTokenCount"}, {"type": "uint256", "name": "maxCost"}], "constant": false, "name": "buy", "payable": false, "outputs": [{"type": "uint256", "name": "cost"}], "type": "function"}, {"inputs": [], "constant": true, "name": "FEE_RANGE", "payable": false, "outputs": [{"type": "uint24", "name": ""}], "type": "function"}, {"inputs": [{"type": "address", "name": "_creator"}, {"type": "address", "name": "_eventContract"}, {"type": "address", "name": "_marketMaker"}, {"type": "uint24", "name": "_fee"}], "type": "constructor", "payable": false}, {"inputs": [{"indexed": false, "type": "uint256", "name": "funding"}], "type": "event", "name": "MarketFunding", "anonymous": false}, {"inputs": [], "type": "event", "name": "MarketClosing", "anonymous": false}, {"inputs": [{"indexed": false, "type": "uint256", "name": "fees"}], "type": "event", "name": "FeeWithdrawal", "anonymous": false}, {"inputs": [{"indexed": true, "type": "address", "name": "buyer"}, {"indexed": false, "type": "uint8", "name": "outcomeTokenIndex"}, {"indexed": false, "type": "uint256", "name": "outcomeTokenCount"}, {"indexed": false, "type": "uint256", "name": "cost"}], "type": "event", "name": "OutcomeTokenPurchase", "anonymous": false}, {"inputs": [{"indexed": true, "type": "address", "name": "seller"}, {"indexed": false, "type": "uint8", "name": "outcomeTokenIndex"}, {"indexed": false, "type": "uint256", "name": "outcomeTokenCount"}, {"indexed": false, "type": "uint256", "name": "profit"}], "type": "event", "name": "OutcomeTokenSale", "anonymous": false}, {"inputs": [{"indexed": true, "type": "address", "name": "buyer"}, {"indexed": false, "type": "uint8", "name": "outcomeTokenIndex"}, {"indexed": false, "type": "uint256", "name": "outcomeTokenCount"}, {"indexed": false, "type": "uint256", "name": "cost"}], "type": "event", "name": "OutcomeTokenShortSale", "anonymous": false}]